twosquares.cpython-313-aarch64-linux-gnu.so
twosquares-stubs/__init__.pyi
twosquares-0.0.5.dist-info/METADATA
twosquares-0.0.5.dist-info/WHEEL
twosquares-0.0.5.dist-info/top_level.txt
twosquares-0.0.5.dist-info/RECORD
twosquares-0.0.5.dist-info/licenses/LICENSE
