Metadata-Version: 2.4
Name: twosquares
Version: 0.0.5
Summary: A package for very efficiently decomposing a number n into all possible x**2 + y**2 = n solutions.
Author-email: Ryan Heard <ryanwheard@gmail.com>
License: MIT
Project-URL: Repository, https://github.com/rheard/twosquares
Keywords: math
Classifier: Programming Language :: Python :: 3
Classifier: Programming Language :: Python :: 3.9
Classifier: Programming Language :: Python :: 3.10
Classifier: Programming Language :: Python :: 3.11
Classifier: Programming Language :: Python :: 3.12
Classifier: Programming Language :: Python :: 3.13
Classifier: Programming Language :: Python :: 3.14
Classifier: Programming Language :: Python :: Implementation :: CPython
Requires-Python: >=3.9
License-File: LICENSE
Requires-Dist: sympy<=1.12.1
Requires-Dist: quadint>=0.0.9
Dynamic: license
Dynamic: license-file
